jsoncrawler/__init__.py
jsoncrawler/jsoncrawler.py
jsoncrawler-0.1.0.dist-info/METADATA
jsoncrawler-0.1.0.dist-info/WHEEL
jsoncrawler-0.1.0.dist-info/top_level.txt
jsoncrawler-0.1.0.dist-info/RECORD
