Metadata-Version: 2.1
Name: jsoncrawler
Version: 0.1.0
Summary: Helps retrieve values from a JSON.
Home-page: UNKNOWN
Author: Uzair Shahed Islam
License: UNKNOWN
Platform: UNKNOWN
